src/simplediscord/__init__.py
src/simplediscord/example.py
simplerdiscord-0.1.0.dist-info/METADATA
simplerdiscord-0.1.0.dist-info/WHEEL
simplerdiscord-0.1.0.dist-info/licenses/LICENSE
simplerdiscord-0.1.0.dist-info/RECORD
