Metadata-Version: 2.1
Name: simplerdiscord
Version: 0.1.0
Summary: Discord.py wrapper and handler, easy to use
Author-email: ze-real-one <zerealone.business@gmail.com>
License-File: LICENSE
Classifier: License :: OSI Approved :: MIT License
Classifier: Operating System :: OS Independent
Classifier: Programming Language :: Python :: 3
Requires-Python: >=3.7
